sru_queryer/__init__.py
sru_queryer/cql.py
sru_queryer/exceptions.py
sru_queryer/sru.py
sru_queryer/_base/__init__.py
sru_queryer/_base/_cql_boolean_operators.py
sru_queryer/_base/_cql_modifiers.py
sru_queryer/_base/_exceptions.py
sru_queryer/_base/_raw_cql.py
sru_queryer/_base/_search_clause.py
sru_queryer/_base/_search_retrieve.py
sru_queryer/_base/_sort_key.py
sru_queryer/_base/_sru_aux_formatter.py
sru_queryer/_base/_sru_configuration.py
sru_queryer/_base/_sru_explain_auto_parser.py
sru_queryer/_base/_sru_queryer.py
sru_queryer/_base/_sru_validator.py
sru_queryer-2.1.3.dist-info/LICENSE
sru_queryer-2.1.3.dist-info/METADATA
sru_queryer-2.1.3.dist-info/WHEEL
sru_queryer-2.1.3.dist-info/top_level.txt
sru_queryer-2.1.3.dist-info/RECORD
