Metadata-Version: 2.2
Name: sru-queryer
Version: 2.1.3
Summary: A utility for integrating SRU queries into your applications.
Author-email: Erik Jones <ejones99@umd.edu>
Maintainer-email: USMAI <libclas@umd.edu>
Keywords: sru,library,api
Classifier: Programming Language :: Python :: 3
Classifier: Development Status :: 5 - Production/Stable
Classifier: License :: OSI Approved :: Apache Software License
Requires-Python: >=3.7
License-File: LICENSE
Requires-Dist: requests<3.0,>=2.27.1
Requires-Dist: xmltodict<0.15,>=0.14.0
